pipen_args/__init__.py
pipen_args/defaults.py
pipen_args/parser_.py
pipen_args/plugin.py
pipen_args/procgroup.py
pipen_args/utils.py
pipen_args/version.py
pipen_args-1.1.2.dist-info/METADATA
pipen_args-1.1.2.dist-info/WHEEL
pipen_args-1.1.2.dist-info/entry_points.txt
pipen_args-1.1.2.dist-info/RECORD
