Metadata-Version: 2.4
Name: pipen-args
Version: 1.1.2
Summary: Command-line argument parser for pipen.
License: MIT
Author: pwwang
Author-email: pwwang@pwwang.com
Requires-Python: >=3.9,<4.0
Classifier: License :: OSI Approved :: MIT License
Classifier: Programming Language :: Python :: 3
Classifier: Programming Language :: Python :: 3.9
Classifier: Programming Language :: Python :: 3.10
Classifier: Programming Language :: Python :: 3.11
Classifier: Programming Language :: Python :: 3.12
Classifier: Programming Language :: Python :: 3.13
Classifier: Programming Language :: Python :: 3.14
Requires-Dist: pipen-annotate (>=1.0,<2.0)
Project-URL: Homepage, https://github.com/pwwang/pipen-args
Project-URL: Repository, https://github.com/pwwang/pipen-args
